rvc_inferpy/__init__.py
rvc_inferpy/infer.py
rvc_inferpy/modules.py
rvc_inferpy/pipeline.py
rvc_inferpy/split_audio.py
rvc_inferpy/utils.py
rvc_inferpy/infer_list/__init__.py
rvc_inferpy/infer_list/audio.py
rvc_inferpy/infer_list/fcpe.py
rvc_inferpy/infer_list/rmvpe.py
rvc_inferpy/infer_list/packs/__init__.py
rvc_inferpy/infer_list/packs/attentions.py
rvc_inferpy/infer_list/packs/commons.py
rvc_inferpy/infer_list/packs/models.py
rvc_inferpy/infer_list/packs/modules.py
rvc_inferpy/infer_list/packs/transforms.py
rvc_inferpy-0.9.1.dist-info/LICENSE
rvc_inferpy-0.9.1.dist-info/METADATA
rvc_inferpy-0.9.1.dist-info/WHEEL
rvc_inferpy-0.9.1.dist-info/top_level.txt
rvc_inferpy-0.9.1.dist-info/RECORD
