Metadata-Version: 2.2
Name: rvc_inferpy
Version: 0.9.1
Summary: Easy tools for RVC Inference
Author: TheNeoDev
Author-email: theneodevemail@gmail.com
License: MIT
Classifier: Programming Language :: Python :: 3
Classifier: License :: OSI Approved :: MIT License
Classifier: Operating System :: OS Independent
Requires-Python: >=3.8
License-File: LICENSE
Requires-Dist: av
Requires-Dist: einops
Requires-Dist: edge-tts
Requires-Dist: faiss-cpu<1.8,>=1.7.3
Requires-Dist: ffmpeg-python>=0.2.0
Requires-Dist: fairseq2
Requires-Dist: gtts
Requires-Dist: local_attention
Requires-Dist: pydub<0.26,>=0.25.1
Requires-Dist: praat-parselmouth<0.5,>=0.4.2
Requires-Dist: pyworld<0.4,>=0.3.4
Requires-Dist: resampy<0.5,>=0.4.2
Requires-Dist: torchcrepe<0.1,>=0.0.23
Requires-Dist: torchfcpe>=0.0.4
Provides-Extra: gpu
Requires-Dist: audio-separator==0.30.1; extra == "gpu"
Requires-Dist: torch>=2.0.0; extra == "gpu"
Provides-Extra: cpu
Requires-Dist: audio-separator==0.30.1; extra == "cpu"
Provides-Extra: dev
Requires-Dist: librosa<0.11,>=0.9.1; extra == "dev"
Dynamic: author
Dynamic: author-email
Dynamic: classifier
Dynamic: description
Dynamic: description-content-type
Dynamic: license
Dynamic: provides-extra
Dynamic: requires-dist
Dynamic: requires-python
Dynamic: summary
